surferr/__init__.py
surferr-0.7.dist-info/LICENSE.txt
surferr-0.7.dist-info/METADATA
surferr-0.7.dist-info/WHEEL
surferr-0.7.dist-info/top_level.txt
surferr-0.7.dist-info/RECORD
