Metadata-Version: 2.1
Name: surferr
Version: 0.7
Summary: AI-Powered Website & Webpage Summarizer
Home-page: https://github.com/gautamxgambhir/Surferr
Author: Gautam Gambhir
Author-email: Gautam Gambhir <ggambhir1919@gmail.com>
Project-URL: Homepage, https://github.com/gautamxgambhir/Surferr
Project-URL: Bug Tracker, https://github.com/gautamxgambhir/Surferr
Classifier: Programming Language :: Python :: 3
Classifier: License :: OSI Approved :: MIT License
Classifier: Operating System :: OS Independent
Requires-Python: >=3.12
License-File: LICENSE.txt
